evalmate/__init__.py
evalmate/alignment/__init__.py
evalmate/alignment/aligner.py
evalmate/alignment/segment.py
evalmate/alignment/sequence.py
evalmate/alignment/time.py
evalmate/alignment/utils.py
evalmate/confusion/__init__.py
evalmate/confusion/aggregation.py
evalmate/confusion/confusion.py
evalmate/confusion/event.py
evalmate/confusion/segment.py
evalmate/evaluator/__init__.py
evalmate/evaluator/asr.py
evalmate/evaluator/evaluator.py
evalmate/evaluator/event.py
evalmate/evaluator/kws.py
evalmate/evaluator/outcome.py
evalmate/evaluator/segment.py
evalmate/evaluator/report_templates/__init__.py
evalmate/evaluator/report_templates/asr.txt
evalmate/evaluator/report_templates/asr_confusion.txt
evalmate/evaluator/report_templates/asr_detail.txt
evalmate/evaluator/report_templates/event.txt
evalmate/evaluator/report_templates/event_confusion.txt
evalmate/evaluator/report_templates/kws.txt
evalmate/evaluator/report_templates/segment.txt
evalmate/evaluator/report_templates/segment_detail.txt
evalmate/utils/__init__.py
evalmate/utils/label.py
evalmate/utils/labellist.py
evalmate-0.3.0.dist-info/LICENSE.txt
evalmate-0.3.0.dist-info/METADATA
evalmate-0.3.0.dist-info/RECORD
evalmate-0.3.0.dist-info/WHEEL
evalmate-0.3.0.dist-info/top_level.txt
tests/alignment/__init__.py
tests/alignment/test_segment.py
tests/alignment/test_sequence.py
tests/alignment/test_time.py
tests/alignment/test_utils.py
tests/confusion/__init__.py
tests/confusion/test_aggregation.py
tests/confusion/test_confusion.py
tests/confusion/test_event.py
tests/confusion/test_segment.py
tests/evaluator/__init__.py
tests/evaluator/test_asr.py
tests/evaluator/test_event.py
tests/evaluator/test_kws.py
tests/evaluator/test_outcome.py
tests/evaluator/test_segment.py
tests/resources/__init__.py
tests/utils/__init__.py
tests/utils/test_label.py
tests/utils/test_labellist.py
